corev2.v
module core (
    input clk,
    output [31:0] OUT_PC,
    output [31:0] OUT_IR,
    output [31:0] OUT_AluIn1,
    output [31:0] OUT_AluIn2,
    output [31:0] OUT_AluOut
);

    parameter LW = 7'b000_0011;
    parameter SW = 7'b010_0011;
    parameter BEQ = 7'b110_001;
    parameter NOP = 32'h0000_0013;
    parameter ALUOp = 7'b001_0011;

    reg [31:0] PC;
    reg [31:0] RF [0:31];

    //Pipeline registers
    reg [31:0] IDEX_A, IDEX_B, EXMEM_B, EXMEM_ALUOut, MEMWB_Value;

    //Separate memories
    reg [31:0] IMemory [0:1023], DMemory [0:1023];

    //Registers to pipeline instruction
    reg [31:0] IFID_IR, IDEX_IR, EXMEM_IR, MEMWB_IR;

    wire [4:0] IFID_rs1, IFID_rs2, MEMWB_rd;
    wire [6:0] IDEX_Op, EXMEM_Op, MEMWB_Op;
    wire [31:0] AluIn1, AluIn2;

    assign IFID_rs1 = IFID_IR[19:15]; // rs1 field
    assign IFID_rs2 = IFID_IR[24:20]; // rs2 field
    assign IDEX_Op = IDEX_IR[6:0];    // opcode
    assign IDEX_rs1 = IDEX_IR[19:15];
    assign IDEX_rs2 = IDEX_IR[24:20];
    assign EXMEM_Op = EXMEM_IR[6:0];  // the opcode
    assign EXMEM_rd = EXMEM_IR[11:7];
    assign MEMWB_Op = MEMWB_IR[6:0];  // the opcode
    assign MEMWB_rd = MEMWB_IR[11:7]; // rd field

    assign AluIn1 = IDEX_A;
    assign AluIn2 = IDEX_B;

    wire bypassAluIn1fromMEM; 
    wire bypassAluIn1fromALUinWB;

    wire bypassAluIn2fromMEM; 
    wire bypassAluIn2fromALUinWB;

    wire bypassAluIn1fromLDinWB;
    wire bypassAluIn2fromLDinWB;

    assign bypassAluIn1fromMEM = (IDEX_rs1 == EXMEM_rd) && (IDEX_rs1 != 0) && (EXMEM_Op == ALUOp);
    assign bypassAluIn2fromMEM = (IDEX_rs2 == EXMEM_rd) && (IDEX_rs2 != 0) && (EXMEM_Op == ALUOp);

    assign bypassAluIn1fromALUinWB = (IDEX_rs1 == MEMWB_rd) && (IDEX_rs1 != 0) && (MEMWB_Op == ALUOp);
    assign bypassAluIn2fromALUinWB = (IDEX_rs2 == MEMWB_rd) && (IDEX_rs2 != 0) && (MEMWB_Op == ALUOp);

    assign bypassAluIn1fromLDinWB = (IDEX_rs1 == MEMWB_rd) && (IDEX_rs1 != 0) && (MEMWB_Op == LW);
    assign bypassAluIn2fromLDinWB = (IDEX_rs2 == MEMWB_rd) && (IDEX_rs2 != 0) && (MEMWB_Op == LW);

    
    assign AluIn1 = bypassAluIn1fromMEM ? EXMEM_ALUOut :
    (bypassAluIn1fromALUinWB || bypassAluIn1fromLDinWB) ? MEMWB_Value : IDEX_A;

    assign AluIn2 = bypassAluIn2fromMEM ? EXMEM_ALUOut :
    (bypassAluIn2fromALUinWB || bypassAluIn2fromLDinWB) ? MEMWB_Value : IDEX_B;

    //Init the regs
    integer i;
    initial begin
        IFID_IR = NOP; IDEX_IR = NOP; EXMEM_IR = NOP; MEMWB_IR = NOP;
        PC = 0;
        for (i=0;i<32;i=i+1) RF[i] = 0;
        for (i=0;i<32;i=i+1) IMemory[i] = 32'b0000000_00001_00001_000_00001_001_0011;
    end

    always @(posedge clk) begin
        //IF stage
        IFID_IR <= IMemory[PC >> 2];
        PC <= PC+4;

        //ID stage
        IDEX_A <= RF[IFID_rs1]; 
        IDEX_B <= RF[IFID_rs2]; 
        IDEX_IR <= IFID_IR; 

        //EX stage
        if (IDEX_Op == LW)
            EXMEM_ALUOut <= IDEX_A + {{53{IDEX_IR[31]}}, IDEX_IR[30:20]}; // rs1 + Immediate for load
        else if (IDEX_Op == SW)
            EXMEM_ALUOut <= IDEX_A + {{53{IDEX_IR[31]}}, IDEX_IR [30:25], IDEX_IR[11:7]}; // rs1 + Immediate for store
        else if (IDEX_Op == ALUOp) //If R-Type
            case (IDEX_IR[31:25]) // case for the various R-type instructions. This is case funct7 for R-Type instructions
                0: EXMEM_ALUOut <= AluIn1 + AluIn2; // add operation

                default: EXMEM_ALUOut <= 0;
            endcase

        EXMEM_IR <= IDEX_IR; 

        //MEM stage
        EXMEM_B <= IDEX_B; // pass along the IR & B register
                           // Mem stage of pipeline
        if (EXMEM_Op == ALUOp) 
            MEMWB_Value <= EXMEM_ALUOut; // pass along ALU result
        else if (EXMEM_Op == LW) MEMWB_Value <= DMemory[EXMEM_ALUOut >> 2];
        else if (EXMEM_Op == SW) DMemory[EXMEM_ALUOut >> 2] <= EXMEM_B; //store
        MEMWB_IR <= EXMEM_IR; // pass along IR

        // WB stage
        if (((MEMWB_Op == LW) || (MEMWB_Op == ALUOp)) && (MEMWB_rd != 0))
            RF[MEMWB_rd] <= MEMWB_Value;
    end


    assign OUT_PC = PC;
    assign OUT_IR = IFID_IR;
    assign OUT_AluIn1 = AluIn1;
    assign OUT_AluIn2 = AluIn2;
    assign OUT_AluOut = EXMEM_ALUOut;

endmodule

corev2_tb.v
`timescale 1ms / 1ms
`include "corev2.v"

module bench();
    
    reg CLK;
    wire [31:0] PC;
    wire [31:0] IR;
    wire [31:0] AluIn1;
    wire [31:0] AluIn2;
    wire [31:0] AluOut;

    core uut(.clk(CLK), .OUT_PC(PC), .OUT_IR(IR), .OUT_AluIn1(AluIn1), .OUT_AluIn2(AluIn2), .OUT_AluOut(AluOut));

    initial begin
        $dumpfile("test.vcd");
        $dumpvars(0, bench);

        CLK = 0;
        forever begin
	        #200 CLK = ~CLK;
            $display("PC = %b, IR = %b, AluIn1 = %b, AluIn2 = %b, AluOut = %b", PC, IR, AluIn1, AluIn2, AluOut);
        end
    end
endmodule

test.vcd
$date
	Wed Oct 23 20:30:54 2024
$end
$version
	Icarus Verilog
$end
$timescale
	1ms
$end
$scope module bench $end
$var wire 32 ! PC [31:0] $end
$var wire 32 " IR [31:0] $end
$var wire 32 # AluOut [31:0] $end
$var wire 32 $ AluIn2 [31:0] $end
$var wire 32 % AluIn1 [31:0] $end
$var reg 1 & CLK $end
$scope module uut $end
$var wire 32 ' AluIn1 [31:0] $end
$var wire 32 ( AluIn2 [31:0] $end
$var wire 32 ) OUT_AluIn1 [31:0] $end
$var wire 32 * OUT_AluIn2 [31:0] $end
$var wire 32 + OUT_AluOut [31:0] $end
$var wire 32 , OUT_IR [31:0] $end
$var wire 32 - OUT_PC [31:0] $end
$var wire 1 . bypassAluIn1fromALUinWB $end
$var wire 1 / bypassAluIn1fromLDinWB $end
$var wire 1 0 bypassAluIn1fromMEM $end
$var wire 1 1 bypassAluIn2fromALUinWB $end
$var wire 1 2 bypassAluIn2fromLDinWB $end
$var wire 1 3 bypassAluIn2fromMEM $end
$var wire 1 & clk $end
$var wire 5 4 MEMWB_rd [4:0] $end
$var wire 7 5 MEMWB_Op [6:0] $end
$var wire 5 6 IFID_rs2 [4:0] $end
$var wire 5 7 IFID_rs1 [4:0] $end
$var wire 1 8 IDEX_rs2 $end
$var wire 1 9 IDEX_rs1 $end
$var wire 7 : IDEX_Op [6:0] $end
$var wire 1 ; EXMEM_rd $end
$var wire 7 < EXMEM_Op [6:0] $end
$var parameter 7 = ALUOp $end
$var parameter 7 > BEQ $end
$var parameter 7 ? LW $end
$var parameter 32 @ NOP $end
$var parameter 7 A SW $end
$var reg 32 B EXMEM_ALUOut [31:0] $end
$var reg 32 C EXMEM_B [31:0] $end
$var reg 32 D EXMEM_IR [31:0] $end
$var reg 32 E IDEX_A [31:0] $end
$var reg 32 F IDEX_B [31:0] $end
$var reg 32 G IDEX_IR [31:0] $end
$var reg 32 H IFID_IR [31:0] $end
$var reg 32 I MEMWB_IR [31:0] $end
$var reg 32 J MEMWB_Value [31:0] $end
$var reg 32 K PC [31:0] $end
$var integer 32 L i [31:0] $end
$upscope $end
$upscope $end
$enddefinitions $end
$comment Show the parameter values. $end
$dumpall
b100011 A
b10011 @
b11 ?
b110001 >
b10011 =
$end
#0
$dumpvars
b100000 L
b0 K
bx J
b10011 I
b10011 H
b10011 G
bx F
bx E
b10011 D
bx C
bx B
b10011 <
0;
b10011 :
09
08
b0 7
b0 6
b10011 5
b0 4
03
02
01
00
0/
0.
b0 -
b10011 ,
bx +
bx *
bx )
bx (
bx '
0&
bx %
bx $
bx #
b10011 "
b0 !
$end
#200
b0 $
b0 *
b0 (
b0 %
b0 )
b0 '
b1 7
b1 6
b0 F
b0 E
b100 !
b100 -
b100 K
b100001000000010010011 "
b100001000000010010011 ,
b100001000000010010011 H
1&
#400
0&
#600
19
18
b11 7
b11 6
b0 C
b0 #
b0 +
b0 B
b100001000000010010011 G
b1 $
b1 *
b1 (
b1 F
b1 %
b1 )
b1 '
b1 E
b1000 !
b1000 -
b1000 K
b1100011000000110010011 "
b1100011000000110010011 ,
b1100011000000110010011 H
1&
#800
0&
#1000
13
10
1;
b10 7
b10 6
b0 J
b1 C
b100001000000010010011 D
b10 #
b10 +
b10 B
b1100011000000110010011 G
b1x $
b1x *
b1x (
b11 F
b1x %
b1x )
b1x '
b11 E
b1100 !
b1100 -
b1100 K
b1000010000000100010011 "
b1000010000000100010011 ,
b1000010000000100010011 H
1&
#1200
0&
#1400
00
03
09
08
b1 4
b11 7
b11 6
b100001000000010010011 I
b10 J
b11 C
b1100011000000110010011 D
bx #
bx +
bx B
b1000010000000100010011 G
b10 $
b10 *
b10 (
b10 F
b10 %
b10 )
b10 '
b10 E
b10000 !
b10000 -
b10000 K
b1100011000000110010011 "
b1100011000000110010011 ,
b1100011000000110010011 H
1&
#1600
0&
#1800
0;
19
18
b11 4
b100 7
b100 6
b1100011000000110010011 I
bx J
b10 C
b1000010000000100010011 D
b100 #
b100 +
b100 B
b1100011000000110010011 G
b11 $
b11 *
b11 (
b11 F
b11 %
b11 )
b11 '
b11 E
b10100 !
b10100 -
b10100 K
b10000100000001000010011 "
b10000100000001000010011 ,
b10000100000001000010011 H
1&
#2000
0&
#2200
1;
09
08
b10 4
b101 7
b101 6
b1000010000000100010011 I
b100 J
b11 C
b1100011000000110010011 D
b110 #
b110 +
b110 B
b10000100000001000010011 G
b100 $
b100 *
b100 (
b100 F
b100 %
b100 )
b100 '
b100 E
b11000 !
b11000 -
b11000 K
b10100101000001010010011 "
b10100101000001010010011 ,
b10100101000001010010011 H
1&
#2400
0&
#2600
0;
19
18
b11 4
b10 7
b10 6
b1100011000000110010011 I
b110 J
b100 C
b10000100000001000010011 D
b1000 #
b1000 +
b1000 B
b10100101000001010010011 G
b101 $
b101 *
b101 (
b101 F
b101 %
b101 )
b101 '
b101 E
b11100 !
b11100 -
b11100 K
b1000010000000010010011 "
b1000010000000010010011 ,
b1000010000000010010011 H
1&
#2800
0&
#3000
1;
09
08
b100 4
b1 7
b1 6
b10000100000001000010011 I
b1000 J
b101 C
b10100101000001010010011 D
b1010 #
b1010 +
b1010 B
b1000010000000010010011 G
b100 $
b100 *
b100 (
b100 F
b100 %
b100 )
b100 '
b100 E
b100000 !
b100000 -
b100000 K
b100001000000010010011 "
b100001000000010010011 ,
b100001000000010010011 H
1&
#3200
0&
#3400
10
13
19
18
b101 4
b10100101000001010010011 I
b1010 J
b100 C
b1000010000000010010011 D
b1000 #
b1000 +
b1000 B
b100001000000010010011 G
b0x0x0 $
b0x0x0 *
b0x0x0 (
b10 F
b0x0x0 %
b0x0x0 )
b0x0x0 '
b10 E
b100100 !
b100100 -
b100100 K
1&
#3600
0&
#3800
1.
11
b1 4
bx %
bx )
bx '
bx $
bx *
bx (
b1000010000000010010011 I
b1000 J
b10 C
b100001000000010010011 D
bx #
bx +
bx B
b101000 !
b101000 -
b101000 K
1&
#4000
0&
#4200
b100001000000010010011 I
bx J
b101100 !
b101100 -
b101100 K
1&
#4400
0&
#4600
b1000 F
b1000 E
b110000 !
b110000 -
b110000 K
1&
#4800
0&
#5000
b1000 C
bx F
bx E
b110100 !
b110100 -
b110100 K
1&
#5200
0&
#5400
bx C
b111000 !
b111000 -
b111000 K
1&
#5600
0&
#5800
b111100 !
b111100 -
b111100 K
1&
#6000
0&
#6200
b1000000 !
b1000000 -
b1000000 K
1&
#6400
0&
#6600
b1000100 !
b1000100 -
b1000100 K
1&
#6800
0&
#7000
b1001000 !
b1001000 -
b1001000 K
1&
#7200
0&
#7400
b1001100 !
b1001100 -
b1001100 K
1&
#7600
0&
#7800
b1010000 !
b1010000 -
b1010000 K
1&
#8000
0&
#8200
b1010100 !
b1010100 -
b1010100 K
1&
#8400
0&
#8600
b1011000 !
b1011000 -
b1011000 K
1&
#8800
0&
#9000
b1011100 !
b1011100 -
b1011100 K
1&
#9200
0&
#9400
b1100000 !
b1100000 -
b1100000 K
1&
#9600
0&
#9800
b1100100 !
b1100100 -
b1100100 K
1&
#10000
0&
#10200
b1101000 !
b1101000 -
b1101000 K
1&
#10400
0&
#10600
b1101100 !
b1101100 -
b1101100 K
1&
#10800
0&
#11000
b1110000 !
b1110000 -
b1110000 K
1&
#11200
0&
#11400
b1110100 !
b1110100 -
b1110100 K
1&
#11600
0&
#11800
b1111000 !
b1111000 -
b1111000 K
1&
#12000
0&
#12200
b1111100 !
b1111100 -
b1111100 K
1&
#12400
0&
#12600
b10000000 !
b10000000 -
b10000000 K
1&
#12800
0&
#13000
bx 7
bx 6
b10000100 !
b10000100 -
b10000100 K
bx "
bx ,
bx H
1&
#13200
0&
#13400
x0
x.
x3
x1
x9
x8
bx :
bx G
b10001000 !
b10001000 -
b10001000 K
1&
#13600
0&
#13800
x;
bx <
bx D
b10001100 !
b10001100 -
b10001100 K
1&
#14000
0&
#14200
x/
x2
bx 5
bx 4
bx I
b10010000 !
b10010000 -
b10010000 K
1&
#14400
0&
#14600
b10010100 !
b10010100 -
b10010100 K
1&
#14800
0&
#15000
b10011000 !
b10011000 -
b10011000 K
1&
#15200
0&
#15400
b10011100 !
b10011100 -
b10011100 K
1&
#15600
0&
#15800
b10100000 !
b10100000 -
b10100000 K
1&
#16000
0&
#16200
b10100100 !
b10100100 -
b10100100 K
1&
#16400
0&
#16600
b10101000 !
b10101000 -
b10101000 K
1&
#16800
0&
#17000
b10101100 !
b10101100 -
b10101100 K
1&
#17200
0&
#17400
b10110000 !
b10110000 -
b10110000 K
1&
#17600
0&
#17800
b10110100 !
b10110100 -
b10110100 K
1&
#18000
0&
#18200
b10111000 !
b10111000 -
b10111000 K
1&
#18400
0&
#18600
b10111100 !
b10111100 -
b10111100 K
1&
#18800
0&
#19000
b11000000 !
b11000000 -
b11000000 K
1&
#19200
0&
#19400
b11000100 !
b11000100 -
b11000100 K
1&
#19600
0&
#19800
b11001000 !
b11001000 -
b11001000 K
1&
#20000
0&
#20200
b11001100 !
b11001100 -
b11001100 K
1&
#20400
0&
#20600
b11010000 !
b11010000 -
b11010000 K
1&
#20800
0&
#21000
b11010100 !
b11010100 -
b11010100 K
1&
#21200
0&
#21400
b11011000 !
b11011000 -
b11011000 K
1&
#21600
0&
#21800
b11011100 !
b11011100 -
b11011100 K
1&
#22000
0&
#22200
b11100000 !
b11100000 -
b11100000 K
1&
#22400
0&
#22600
b11100100 !
b11100100 -
b11100100 K
1&
#22800
0&
#23000
b11101000 !
b11101000 -
b11101000 K
1&
#23200
0&
#23400
b11101100 !
b11101100 -
b11101100 K
1&
#23600
0&
#23800
b11110000 !
b11110000 -
b11110000 K
1&
#24000
0&
#24200
b11110100 !
b11110100 -
b11110100 K
1&
#24400
0&
#24600
b11111000 !
b11111000 -
b11111000 K
1&
#24800
0&
#25000
b11111100 !
b11111100 -
b11111100 K
1&
#25200
0&
#25400
b100000000 !
b100000000 -
b100000000 K
1&
#25600
0&
#25800
b100000100 !
b100000100 -
b100000100 K
1&
#26000
0&
#26200
b100001000 !
b100001000 -
b100001000 K
1&
#26400
0&
#26600
b100001100 !
b100001100 -
b100001100 K
1&
#26800
0&
#27000
b100010000 !
b100010000 -
b100010000 K
1&
#27200
0&
#27400
b100010100 !
b100010100 -
b100010100 K
1&
#27600
0&
#27800
b100011000 !
b100011000 -
b100011000 K
1&
#28000
0&
#28200
b100011100 !
b100011100 -
b100011100 K
1&
#28400
0&
#28600
b100100000 !
b100100000 -
b100100000 K
1&
#28800
0&
#29000
b100100100 !
b100100100 -
b100100100 K
1&
#29200
0&
#29400
b100101000 !
b100101000 -
b100101000 K
1&
#29600
0&
#29800
b100101100 !
b100101100 -
b100101100 K
1&
#30000
0&
#30200
b100110000 !
b100110000 -
b100110000 K
1&
#30400
0&
#30600
b100110100 !
b100110100 -
b100110100 K
1&
#30800
0&
#31000
b100111000 !
b100111000 -
b100111000 K
1&
#31200
0&
#31400
b100111100 !
b100111100 -
b100111100 K
1&
#31600
0&
#31800
b101000000 !
b101000000 -
b101000000 K
1&
#32000
0&
#32200
b101000100 !
b101000100 -
b101000100 K
1&
#32400
0&
#32600
b101001000 !
b101001000 -
b101001000 K
1&
#32800
0&
#33000
b101001100 !
b101001100 -
b101001100 K
1&
#33200
0&
#33400
b101010000 !
b101010000 -
b101010000 K
1&
#33600
0&
#33800
b101010100 !
b101010100 -
b101010100 K
1&
#34000
0&
#34200
b101011000 !
b101011000 -
b101011000 K
1&
#34400
0&
#34600
b101011100 !
b101011100 -
b101011100 K
1&
#34800
0&
#35000
b101100000 !
b101100000 -
b101100000 K
1&
#35200
0&
#35400
b101100100 !
b101100100 -
b101100100 K
1&
#35600
0&
#35800
b101101000 !
b101101000 -
b101101000 K
1&
#36000
0&
#36200
b101101100 !
b101101100 -
b101101100 K
1&
#36400
0&
#36600
b101110000 !
b101110000 -
b101110000 K
1&
#36800
0&
#37000
b101110100 !
b101110100 -
b101110100 K
1&
#37200
0&
#37400
b101111000 !
b101111000 -
b101111000 K
1&
#37600
0&
#37800
b101111100 !
b101111100 -
b101111100 K
1&
#38000
0&
#38200
b110000000 !
b110000000 -
b110000000 K
1&
#38400
0&
#38600
b110000100 !
b110000100 -
b110000100 K
1&
#38800
0&
#39000
b110001000 !
b110001000 -
b110001000 K
1&
#39200
0&
#39400
b110001100 !
b110001100 -
b110001100 K
1&
#39600
0&
#39800
b110010000 !
b110010000 -
b110010000 K
1&
#40000
0&
#40200
b110010100 !
b110010100 -
b110010100 K
1&
#40400
0&
#40600
b110011000 !
b110011000 -
b110011000 K
1&
#40800
0&
#41000
b110011100 !
b110011100 -
b110011100 K
1&
#41200
0&
#41400
b110100000 !
b110100000 -
b110100000 K
1&
#41600
0&
#41800
b110100100 !
b110100100 -
b110100100 K
1&
#42000
0&
#42200
b110101000 !
b110101000 -
b110101000 K
1&
#42400
0&
#42600
b110101100 !
b110101100 -
b110101100 K
1&
#42800
0&
#43000
b110110000 !
b110110000 -
b110110000 K
1&
#43200
0&
#43400
b110110100 !
b110110100 -
b110110100 K
1&
#43600
0&
#43800
b110111000 !
b110111000 -
b110111000 K
1&
#44000
0&
#44200
b110111100 !
b110111100 -
b110111100 K
1&
#44400
0&
#44600
b111000000 !
b111000000 -
b111000000 K
1&
#44800
0&
#45000
b111000100 !
b111000100 -
b111000100 K
1&
#45200
0&
#45400
b111001000 !
b111001000 -
b111001000 K
1&
#45600
0&
#45800
b111001100 !
b111001100 -
b111001100 K
1&
#46000
0&
#46200
b111010000 !
b111010000 -
b111010000 K
1&
#46400
0&
#46600
b111010100 !
b111010100 -
b111010100 K
1&
#46800
0&
#47000
b111011000 !
b111011000 -
b111011000 K
1&
#47200
0&
#47400
b111011100 !
b111011100 -
b111011100 K
1&
#47600
0&
#47800
b111100000 !
b111100000 -
b111100000 K
1&
#48000
0&
#48200
b111100100 !
b111100100 -
b111100100 K
1&
#48400
0&
#48600
b111101000 !
b111101000 -
b111101000 K
1&
#48800
0&
#49000
b111101100 !
b111101100 -
b111101100 K
1&
#49200
0&
#49400
b111110000 !
b111110000 -
b111110000 K
1&
#49600
0&
#49800
b111110100 !
b111110100 -
b111110100 K
1&
#50000
0&
#50200
b111111000 !
b111111000 -
b111111000 K
1&
#50400
0&
#50600
b111111100 !
b111111100 -
b111111100 K
1&
#50800
0&
#51000
b1000000000 !
b1000000000 -
b1000000000 K
1&
#51200
0&
#51400
b1000000100 !
b1000000100 -
b1000000100 K
1&
#51600
0&
#51800
b1000001000 !
b1000001000 -
b1000001000 K
1&
#52000
0&
#52200
b1000001100 !
b1000001100 -
b1000001100 K
1&
#52400
0&
#52600
b1000010000 !
b1000010000 -
b1000010000 K
1&
#52800
0&
#53000
b1000010100 !
b1000010100 -
b1000010100 K
1&
#53200
0&
#53400
b1000011000 !
b1000011000 -
b1000011000 K
1&
#53600
0&
#53800
b1000011100 !
b1000011100 -
b1000011100 K
1&
#54000
0&
#54200
b1000100000 !
b1000100000 -
b1000100000 K
1&
#54400
0&
#54600
b1000100100 !
b1000100100 -
b1000100100 K
1&
#54800
0&
#55000
b1000101000 !
b1000101000 -
b1000101000 K
1&
#55200
0&
#55400
b1000101100 !
b1000101100 -
b1000101100 K
1&
#55600
0&
#55800
b1000110000 !
b1000110000 -
b1000110000 K
1&
#56000
0&
#56200
b1000110100 !
b1000110100 -
b1000110100 K
1&
#56400
0&
#56600
b1000111000 !
b1000111000 -
b1000111000 K
1&
#56800
0&
#57000
b1000111100 !
b1000111100 -
b1000111100 K
1&
#57200
0&
#57400
b1001000000 !
b1001000000 -
b1001000000 K
1&
#57600
0&
#57800
b1001000100 !
b1001000100 -
b1001000100 K
1&
#58000
0&
#58200
b1001001000 !
b1001001000 -
b1001001000 K
1&
#58400
0&
#58600
b1001001100 !
b1001001100 -
b1001001100 K
1&
#58800
0&
#59000
b1001010000 !
b1001010000 -
b1001010000 K
1&
#59200
0&
#59400
b1001010100 !
b1001010100 -
b1001010100 K
1&
#59600
0&
#59800
b1001011000 !
b1001011000 -
b1001011000 K
1&
#60000
0&
#60200
b1001011100 !
b1001011100 -
b1001011100 K
1&
#60400
0&
#60600
b1001100000 !
b1001100000 -
b1001100000 K
1&
#60800
0&
#61000
b1001100100 !
b1001100100 -
b1001100100 K
1&
#61200
0&
#61400
b1001101000 !
b1001101000 -
b1001101000 K
1&
#61600
0&
#61800
b1001101100 !
b1001101100 -
b1001101100 K
1&
#62000
0&
#62200
b1001110000 !
b1001110000 -
b1001110000 K
1&
#62400
0&
#62600
b1001110100 !
b1001110100 -
b1001110100 K
1&
#62800
0&
#63000
b1001111000 !
b1001111000 -
b1001111000 K
1&
#63200
0&
#63400
b1001111100 !
b1001111100 -
b1001111100 K
1&
#63600
0&
#63800
b1010000000 !
b1010000000 -
b1010000000 K
1&
#64000
0&
#64200
b1010000100 !
b1010000100 -
b1010000100 K
1&
#64400
0&
#64600
b1010001000 !
b1010001000 -
b1010001000 K
1&
#64800
0&
#65000
b1010001100 !
b1010001100 -
b1010001100 K
1&
#65200
0&
#65400
b1010010000 !
b1010010000 -
b1010010000 K
1&
#65600
0&
#65800
b1010010100 !
b1010010100 -
b1010010100 K
1&
#66000
0&
#66200
b1010011000 !
b1010011000 -
b1010011000 K
1&
#66400
0&
#66600
b1010011100 !
b1010011100 -
b1010011100 K
1&
#66800
0&
#67000
b1010100000 !
b1010100000 -
b1010100000 K
1&
#67200
0&
#67400
b1010100100 !
b1010100100 -
b1010100100 K
1&
#67600
0&
#67800
b1010101000 !
b1010101000 -
b1010101000 K
1&
#68000
0&
#68200
b1010101100 !
b1010101100 -
b1010101100 K
1&
#68400
0&
#68600
b1010110000 !
b1010110000 -
b1010110000 K
1&
#68800
0&
#69000
b1010110100 !
b1010110100 -
b1010110100 K
1&
#69200
0&
#69400
b1010111000 !
b1010111000 -
b1010111000 K
1&
#69600
0&
#69800
b1010111100 !
b1010111100 -
b1010111100 K
1&
#70000
0&
#70200
b1011000000 !
b1011000000 -
b1011000000 K
1&
#70400
0&
#70600
b1011000100 !
b1011000100 -
b1011000100 K
1&
#70800
0&
#71000
b1011001000 !
b1011001000 -
b1011001000 K
1&
#71200
0&
#71400
b1011001100 !
b1011001100 -
b1011001100 K
1&
#71600
0&
#71800
b1011010000 !
b1011010000 -
b1011010000 K
1&
#72000
0&
#72200
b1011010100 !
b1011010100 -
b1011010100 K
1&
#72400
0&
#72600
b1011011000 !
b1011011000 -
b1011011000 K
1&
#72800
0&
#73000
b1011011100 !
b1011011100 -
b1011011100 K
1&
#73200
0&
#73400
b1011100000 !
b1011100000 -
b1011100000 K
1&
#73600
0&
#73800
b1011100100 !
b1011100100 -
b1011100100 K
1&
#74000
0&
#74200
b1011101000 !
b1011101000 -
b1011101000 K
1&
#74400
0&
#74600
b1011101100 !
b1011101100 -
b1011101100 K
1&
#74800
0&
#75000
b1011110000 !
b1011110000 -
b1011110000 K
1&
#75200
0&
#75400
b1011110100 !
b1011110100 -
b1011110100 K
1&
#75600
0&
#75800
b1011111000 !
b1011111000 -
b1011111000 K
1&
#76000
0&
#76200
b1011111100 !
b1011111100 -
b1011111100 K
1&
#76400
0&
#76600
b1100000000 !
b1100000000 -
b1100000000 K
1&
#76800
0&
#77000
b1100000100 !
b1100000100 -
b1100000100 K
1&
#77200
0&
#77400
b1100001000 !
b1100001000 -
b1100001000 K
1&
#77600
0&
#77800
b1100001100 !
b1100001100 -
b1100001100 K
1&
#78000
0&
#78200
b1100010000 !
b1100010000 -
b1100010000 K
1&
#78400
0&
#78600
b1100010100 !
b1100010100 -
b1100010100 K
1&
#78800
0&
#79000
b1100011000 !
b1100011000 -
b1100011000 K
1&
#79200
0&
#79400
b1100011100 !
b1100011100 -
b1100011100 K
1&
#79600
0&
#79800
b1100100000 !
b1100100000 -
b1100100000 K
1&
#80000
0&
#80200
b1100100100 !
b1100100100 -
b1100100100 K
1&
#80400
0&
#80600
b1100101000 !
b1100101000 -
b1100101000 K
1&
#80800
0&
#81000
b1100101100 !
b1100101100 -
b1100101100 K
1&
#81200
0&
#81400
b1100110000 !
b1100110000 -
b1100110000 K
1&
#81600
0&
#81800
b1100110100 !
b1100110100 -
b1100110100 K
1&
#82000
0&
#82200
b1100111000 !
b1100111000 -
b1100111000 K
1&
#82400
0&
#82600
b1100111100 !
b1100111100 -
b1100111100 K
1&
#82800
0&
#83000
b1101000000 !
b1101000000 -
b1101000000 K
1&
#83200
0&
#83400
b1101000100 !
b1101000100 -
b1101000100 K
1&
#83600
0&
#83800
b1101001000 !
b1101001000 -
b1101001000 K
1&
#84000
0&
#84200
b1101001100 !
b1101001100 -
b1101001100 K
1&
#84400
0&
#84600
b1101010000 !
b1101010000 -
b1101010000 K
1&
#84800
0&
#85000
b1101010100 !
b1101010100 -
b1101010100 K
1&
#85200
0&
#85400
b1101011000 !
b1101011000 -
b1101011000 K
1&
#85600
0&
#85800
b1101011100 !
b1101011100 -
b1101011100 K
1&
#86000
0&
#86200
b1101100000 !
b1101100000 -
b1101100000 K
1&
#86400
0&
#86600
b1101100100 !
b1101100100 -
b1101100100 K
1&
#86800
0&
#87000
b1101101000 !
b1101101000 -
b1101101000 K
1&
#87200
0&
#87400
b1101101100 !
b1101101100 -
b1101101100 K
1&
#87600
0&
#87800
b1101110000 !
b1101110000 -
b1101110000 K
1&
#88000
0&
#88200
b1101110100 !
b1101110100 -
b1101110100 K
1&
#88400
0&
#88600
b1101111000 !
b1101111000 -
b1101111000 K
1&
#88800
0&
#89000
b1101111100 !
b1101111100 -
b1101111100 K
1&
#89200
0&
#89400
b1110000000 !
b1110000000 -
b1110000000 K
1&
#89600
0&
#89800
b1110000100 !
b1110000100 -
b1110000100 K
1&
#90000
0&
#90200
b1110001000 !
b1110001000 -
b1110001000 K
1&
#90400
0&
#90600
b1110001100 !
b1110001100 -
b1110001100 K
1&
#90800
0&
#91000
b1110010000 !
b1110010000 -
b1110010000 K
1&
#91200
0&
#91400
b1110010100 !
b1110010100 -
b1110010100 K
1&
#91600
0&
#91800
b1110011000 !
b1110011000 -
b1110011000 K
1&
#92000
0&
#92200
b1110011100 !
b1110011100 -
b1110011100 K
1&
#92400
0&
#92600
b1110100000 !
b1110100000 -
b1110100000 K
1&
#92800
0&
#93000
b1110100100 !
b1110100100 -
b1110100100 K
1&
#93200
0&
#93400
b1110101000 !
b1110101000 -
b1110101000 K
1&
#93600
0&
#93800
b1110101100 !
b1110101100 -
b1110101100 K
1&
#94000
0&
#94200
b1110110000 !
b1110110000 -
b1110110000 K
1&
#94400
0&
#94600
b1110110100 !
b1110110100 -
b1110110100 K
1&
#94800
0&
#95000
b1110111000 !
b1110111000 -
b1110111000 K
1&
#95200
0&
#95400
b1110111100 !
b1110111100 -
b1110111100 K
1&
#95600
0&
#95800
b1111000000 !
b1111000000 -
b1111000000 K
1&
#96000
0&
#96200
b1111000100 !
b1111000100 -
b1111000100 K
1&
#96400
0&
#96600
b1111001000 !
b1111001000 -
b1111001000 K
1&
#96800
0&
#97000
b1111001100 !
b1111001100 -
b1111001100 K
1&
#97200
0&
#97400
b1111010000 !
b1111010000 -
b1111010000 K
1&
#97600
0&
#97800
b1111010100 !
b1111010100 -
b1111010100 K
1&
#98000
0&
#98200
b1111011000 !
b1111011000 -
b1111011000 K
1&
#98400
0&
#98600
b1111011100 !
b1111011100 -
b1111011100 K
1&
#98800
0&
#99000
b1111100000 !
b1111100000 -
b1111100000 K
1&
#99200
0&
#99400
b1111100100 !
b1111100100 -
b1111100100 K
1&
#99600
0&
#99800
b1111101000 !
b1111101000 -
b1111101000 K
1&
#100000
0&
#100200
b1111101100 !
b1111101100 -
b1111101100 K
1&
#100400
0&
#100600
b1111110000 !
b1111110000 -
b1111110000 K
1&
#100800
0&
#101000
b1111110100 !
b1111110100 -
b1111110100 K
1&
#101200
0&
#101400
b1111111000 !
b1111111000 -
b1111111000 K
1&
#101600
0&
#101800
b1111111100 !
b1111111100 -
b1111111100 K
1&
#102000
0&
#102200
b10000000000 !
b10000000000 -
b10000000000 K
1&
#102400
0&
